{"DA Warner":{"dismissedPlayer":"Harbhajan Singh","numberOfdismissals":3},"S Dhawan":{"dismissedPlayer":"P Kumar","numberOfdismissals":4},"MC Henriques":{"dismissedPlayer":"SR Watson","numberOfdismissals":2},"Yuvraj Singh":{"dismissedPlayer":"SL Malinga","numberOfdismissals":3},"Mandeep Singh":{"dismissedPlayer":"MM Sharma","numberOfdismissals":3},"CH Gayle":{"dismissedPlayer":"Sandeep Sharma","numberOfdismissals":4},"KM Jadhav":{"dismissedPlayer":"JD Unadkat","numberOfdismissals":2},"TM Head":{"dismissedPlayer":"Rashid Khan","numberOfdismissals":1},"Sachin Baby":{"dismissedPlayer":"Bipul Sharma","numberOfdismissals":1},"STR Binny":{"dismissedPlayer":"KA Pollard","numberOfdismissals":2},"SR Watson":{"dismissedPlayer":"AR Patel","numberOfdismissals":5},"S Aravind":{"dismissedPlayer":"A Nehra","numberOfdismissals":1},"TS Mills":{"dismissedPlayer":"B Kumar","numberOfdismissals":1},"YS Chahal":{"dismissedPlayer":"BCJ Cutting","numberOfdismissals":1},"PA Patel":{"dismissedPlayer":"B Kumar","numberOfdismissals":5},"RG Sharma":{"dismissedPlayer":"R Vinay Kumar","numberOfdismissals":6},"JC Buttler":{"dismissedPlayer":"A Nehra","numberOfdismissals":2},"AT Rayudu":{"dismissedPlayer":"MM Sharma","numberOfdismissals":5},"KH Pandya":{"dismissedPlayer":"R Bhatia","numberOfdismissals":1},"N Rana":{"dismissedPlayer":"A Zampa","numberOfdismissals":1},"KA Pollard":{"dismissedPlayer":"B Kumar","numberOfdismissals":3},"TG Southee":{"dismissedPlayer":"AB Dinda","numberOfdismissals":1},"MA Agarwal":{"dismissedPlayer":"R Ashwin","numberOfdismissals":3},"AM Rahane":{"dismissedPlayer":"B Kumar","numberOfdismissals":6},"BA Stokes":{"dismissedPlayer":"HH Pandya","numberOfdismissals":1},"JJ Roy":{"dismissedPlayer":"PP Chawla","numberOfdismissals":1},"BB McCullum":{"dismissedPlayer":"SL Malinga","numberOfdismissals":4},"AJ Finch":{"dismissedPlayer":"P Negi","numberOfdismissals":3},"KD Karthik":{"dismissedPlayer":"DW Steyn","numberOfdismissals":4},"SPD Smith":{"dismissedPlayer":"RA Jadeja","numberOfdismissals":4},"MS Dhoni":{"dismissedPlayer":"Z Khan","numberOfdismissals":7},"DT Christian":{"dismissedPlayer":"UT Yadav","numberOfdismissals":2},"M Vohra":{"dismissedPlayer":"PP Chawla","numberOfdismissals":2},"WP Saha":{"dismissedPlayer":"DJ Bravo","numberOfdismissals":3},"HM Amla":{"dismissedPlayer":"B Kumar","numberOfdismissals":2},"AR Patel":{"dismissedPlayer":"SP Narine","numberOfdismissals":3},"Vishnu Vinod":{"dismissedPlayer":"Z Khan","numberOfdismissals":1},"P Negi":{"dismissedPlayer":"CH Morris","numberOfdismissals":2},"AP Tare":{"dismissedPlayer":"KK Cooper","numberOfdismissals":2},"KK Nair":{"dismissedPlayer":"Harbhajan Singh","numberOfdismissals":4},"SW Billings":{"dismissedPlayer":"Iqbal Abdulla","numberOfdismissals":1},"SV Samson":{"dismissedPlayer":"MJ McClenaghan","numberOfdismissals":4},"CH Morris":{"dismissedPlayer":"UT Yadav","numberOfdismissals":2},"CR Brathwaite":{"dismissedPlayer":"YS Chahal","numberOfdismissals":1},"PJ Cummins":{"dismissedPlayer":"SR Watson","numberOfdismissals":1},"RR Pant":{"dismissedPlayer":"JJ Bumrah","numberOfdismissals":3},"S Nadeem":{"dismissedPlayer":"P Negi","numberOfdismissals":2},"SK Raina":{"dismissedPlayer":"Harbhajan Singh","numberOfdismissals":5},"DR Smith":{"dismissedPlayer":"Harbhajan Singh","numberOfdismissals":4},"DS Kulkarni":{"dismissedPlayer":"CJ Jordan","numberOfdismissals":2},"G Gambhir":{"dismissedPlayer":"Z Khan","numberOfdismissals":6},"RV Uthappa":{"dismissedPlayer":"A Mishra","numberOfdismissals":5},"CA Lynn":{"dismissedPlayer":"JJ Bumrah","numberOfdismissals":2},"YK Pathan":{"dismissedPlayer":"R Vinay Kumar","numberOfdismissals":4},"SA Yadav":{"dismissedPlayer":"JP Faulkner","numberOfdismissals":2},"CR Woakes":{"dismissedPlayer":"SL Malinga","numberOfdismissals":1},"SP Narine":{"dismissedPlayer":"MG Johnson","numberOfdismissals":2},"RA Tripathi":{"dismissedPlayer":"P Negi","numberOfdismissals":2},"F du Plessis":{"dismissedPlayer":"SL Malinga","numberOfdismissals":4},"R Bhatia":{"dismissedPlayer":"Harbhajan Singh","numberOfdismissals":2},"DL Chahar":{"dismissedPlayer":"Z Khan","numberOfdismissals":1},"A Zampa":{"dismissedPlayer":"A Mishra","numberOfdismissals":1},"AB Dinda":{"dismissedPlayer":"SL Malinga","numberOfdismissals":2},"DJ Hooda":{"dismissedPlayer":"MM Sharma","numberOfdismissals":2},"BCJ Cutting":{"dismissedPlayer":"JJ Bumrah","numberOfdismissals":1},"V Shankar":{"dismissedPlayer":"SL Malinga","numberOfdismissals":1},"NV Ojha":{"dismissedPlayer":"RP Singh","numberOfdismissals":4},"Rashid Khan":{"dismissedPlayer":"JJ Bumrah","numberOfdismissals":1},"MP Stoinis":{"dismissedPlayer":"SP Narine","numberOfdismissals":1},"GJ Maxwell":{"dismissedPlayer":"A Mishra","numberOfdismissals":4},"DA Miller":{"dismissedPlayer":"UT Yadav","numberOfdismissals":3},"MM Sharma":{"dismissedPlayer":"MA Starc","numberOfdismissals":2},"VR Aaron":{"dismissedPlayer":"CR Woakes","numberOfdismissals":1},"V Kohli":{"dismissedPlayer":"A Nehra","numberOfdismissals":6},"AB de Villiers":{"dismissedPlayer":"PP Chawla","numberOfdismissals":5},"MJ McClenaghan":{"dismissedPlayer":"S Badree","numberOfdismissals":1},"Ankit Sharma":{"dismissedPlayer":"AJ Tye","numberOfdismissals":1},"MK Tiwary":{"dismissedPlayer":"M Morkel","numberOfdismissals":4},"SN Thakur":{"dismissedPlayer":"AJ Tye","numberOfdismissals":1},"MK Pandey":{"dismissedPlayer":"Harbhajan Singh","numberOfdismissals":5},"C de Grandhomme":{"dismissedPlayer":"B Kumar","numberOfdismissals":1},"SS Iyer":{"dismissedPlayer":"Sandeep Sharma","numberOfdismissals":3},"EJG Morgan":{"dismissedPlayer":"R Vinay Kumar","numberOfdismissals":2},"KC Cariappa":{"dismissedPlayer":"CH Morris","numberOfdismissals":1},"Ishan Kishan":{"dismissedPlayer":"Imran Tahir","numberOfdismissals":2},"S Badree":{"dismissedPlayer":"JD Unadkat","numberOfdismissals":1},"AF Milne":{"dismissedPlayer":"BA Stokes","numberOfdismissals":1},"AD Mathews":{"dismissedPlayer":"R Vinay Kumar","numberOfdismissals":3},"Mohammad Nabi":{"dismissedPlayer":"Sandeep Sharma","numberOfdismissals":1},"I Sharma":{"dismissedPlayer":"S Kaul","numberOfdismissals":1},"RA Jadeja":{"dismissedPlayer":"A Mishra","numberOfdismissals":4},"KS Williamson":{"dismissedPlayer":"CH Morris","numberOfdismissals":2},"SE Marsh":{"dismissedPlayer":"B Kumar","numberOfdismissals":3},"Harbhajan Singh":{"dismissedPlayer":"P Kumar","numberOfdismissals":4},"HH Pandya":{"dismissedPlayer":"Mustafizur Rahman","numberOfdismissals":2},"CJ Anderson":{"dismissedPlayer":"SP Narine","numberOfdismissals":2},"K Rabada":{"dismissedPlayer":"JJ Bumrah","numberOfdismissals":1},"AD Nath":{"dismissedPlayer":"KC Cariappa","numberOfdismissals":1},"AJ Tye":{"dismissedPlayer":"Sandeep Sharma","numberOfdismissals":1},"NM Coulter-Nile":{"dismissedPlayer":"P Negi","numberOfdismissals":1},"Kuldeep Yadav":{"dismissedPlayer":"S Aravind","numberOfdismissals":1},"KV Sharma":{"dismissedPlayer":"SR Watson","numberOfdismissals":2},"MJ Guptill":{"dismissedPlayer":"B Kumar","numberOfdismissals":2},"Anureet Singh":{"dismissedPlayer":"A Nehra","numberOfdismissals":1},"IK Pathan":{"dismissedPlayer":"Z Khan","numberOfdismissals":3},"JP Faulkner":{"dismissedPlayer":"B Kumar","numberOfdismissals":2},"JJ Bumrah":{"dismissedPlayer":"IK Pathan","numberOfdismissals":1},"Mohammed Shami":{"dismissedPlayer":"VR Aaron","numberOfdismissals":1},"SP Jackson":{"dismissedPlayer":"B Kumar","numberOfdismissals":1},"PJ Sangwan":{"dismissedPlayer":"JD Unadkat","numberOfdismissals":1},"Ankit Soni":{"dismissedPlayer":"JD Unadkat","numberOfdismissals":1},"A Choudhary":{"dismissedPlayer":"MM Sharma","numberOfdismissals":1},"Bipul Sharma":{"dismissedPlayer":"JD Unadkat","numberOfdismissals":1},"B Kumar":{"dismissedPlayer":"RP Singh","numberOfdismissals":2},"LMP Simmons":{"dismissedPlayer":"R Ashwin","numberOfdismissals":2},"MN Samuels":{"dismissedPlayer":"KV Sharma","numberOfdismissals":1},"Z Khan":{"dismissedPlayer":"DE Bollinger","numberOfdismissals":2},"Swapnil Singh":{"dismissedPlayer":"CR Woakes","numberOfdismissals":1},"P Kumar":{"dismissedPlayer":"SL Malinga","numberOfdismissals":3},"MM Patel":{"dismissedPlayer":"A Kumble","numberOfdismissals":2},"SS Tiwary":{"dismissedPlayer":"PP Chawla","numberOfdismissals":2},"R Tewatia":{"dismissedPlayer":"SN Thakur","numberOfdismissals":1},"A Mishra":{"dismissedPlayer":"SL Malinga","numberOfdismissals":2},"CJ Jordan":{"dismissedPlayer":"NM Coulter-Nile","numberOfdismissals":1},"IR Jaggi":{"dismissedPlayer":"KV Sharma","numberOfdismissals":1},"PP Chawla":{"dismissedPlayer":"SL Malinga","numberOfdismissals":3},"AS Rajpoot":{"dismissedPlayer":"SL Malinga","numberOfdismissals":1},"Washington Sundar":{"dismissedPlayer":"MG Johnson","numberOfdismissals":1},"SC Ganguly":{"dismissedPlayer":"R Vinay Kumar","numberOfdismissals":4},"RT Ponting":{"dismissedPlayer":"JH Kallis","numberOfdismissals":1},"DJ Hussey":{"dismissedPlayer":"SK Trivedi","numberOfdismissals":4},"R Dravid":{"dismissedPlayer":"Harbhajan Singh","numberOfdismissals":4},"JH Kallis":{"dismissedPlayer":"RP Singh","numberOfdismissals":4},"W Jaffer":{"dismissedPlayer":"AB Dinda","numberOfdismissals":1},"MV Boucher":{"dismissedPlayer":"RP Singh","numberOfdismissals":2},"B Akhil":{"dismissedPlayer":"AB Agarkar","numberOfdismissals":1},"CL White":{"dismissedPlayer":"R Vinay Kumar","numberOfdismissals":2},"AA Noffke":{"dismissedPlayer":"SC Ganguly","numberOfdismissals":1},"SB Joshi":{"dismissedPlayer":"LR Shukla","numberOfdismissals":1},"ML Hayden":{"dismissedPlayer":"A Nehra","numberOfdismissals":2},"JDP Oram":{"dismissedPlayer":"IK Pathan","numberOfdismissals":2},"K Goel":{"dismissedPlayer":"MS Gony","numberOfdismissals":2},"JR Hopes":{"dismissedPlayer":"P Amarnath","numberOfdismissals":1},"KC Sangakkara":{"dismissedPlayer":"R Sharma","numberOfdismissals":5},"T Kohli":{"dismissedPlayer":"GD McGrath","numberOfdismissals":1},"DS Lehmann":{"dismissedPlayer":"MF Maharoof","numberOfdismissals":1},"M Kaif":{"dismissedPlayer":"S Sreesanth","numberOfdismissals":2},"M Rawat":{"dismissedPlayer":"R Bhatia","numberOfdismissals":1},"SK Warne":{"dismissedPlayer":"A Mishra","numberOfdismissals":3},"V Sehwag":{"dismissedPlayer":"SR Watson","numberOfdismissals":3},"L Ronchi":{"dismissedPlayer":"Z Khan","numberOfdismissals":1},"DJ Thornely":{"dismissedPlayer":"Z Khan","numberOfdismissals":1},"ST Jayasuriya":{"dismissedPlayer":"B Lee","numberOfdismissals":2},"PR Shah":{"dismissedPlayer":"B Akhil","numberOfdismissals":1},"AM Nayar":{"dismissedPlayer":"IK Pathan","numberOfdismissals":2},"SM Pollock":{"dismissedPlayer":"Z Khan","numberOfdismissals":1},"S Chanderpaul":{"dismissedPlayer":"DS Kulkarni","numberOfdismissals":1},"LRPL Taylor":{"dismissedPlayer":"PP Ojha","numberOfdismissals":3},"Y Venugopal Rao":{"dismissedPlayer":"SL Malinga","numberOfdismissals":3},"VVS Laxman":{"dismissedPlayer":"AB Dinda","numberOfdismissals":2},"AC Gilchrist":{"dismissedPlayer":"IK Pathan","numberOfdismissals":4},"SB Styris":{"dismissedPlayer":"Mohammad Hafeez","numberOfdismissals":1},"AS Yadav":{"dismissedPlayer":"DJ Hussey","numberOfdismissals":1},"A Symonds":{"dismissedPlayer":"A Mishra","numberOfdismissals":3},"WPUJC Vaas":{"dismissedPlayer":"AB Agarkar","numberOfdismissals":1},"SB Bangar":{"dismissedPlayer":"M Kartik","numberOfdismissals":1},"PP Ojha":{"dismissedPlayer":"SK Raina","numberOfdismissals":2},"Mohammad Hafeez":{"dismissedPlayer":"PP Ojha","numberOfdismissals":1},"DPMD Jayawardene":{"dismissedPlayer":"M Muralitharan","numberOfdismissals":3},"B Lee":{"dismissedPlayer":"SK Trivedi","numberOfdismissals":1},"S Sohal":{"dismissedPlayer":"RP Singh","numberOfdismissals":2},"Kamran Akmal":{"dismissedPlayer":"JR Hopes","numberOfdismissals":1},"Shahid Afridi":{"dismissedPlayer":"R Bhatia","numberOfdismissals":1},"MEK Hussey":{"dismissedPlayer":"Z Khan","numberOfdismissals":4},"DJ Bravo":{"dismissedPlayer":"RP Singh","numberOfdismissals":3},"MA Khote":{"dismissedPlayer":"M Muralitharan","numberOfdismissals":1},"GC Smith":{"dismissedPlayer":"P Kumar","numberOfdismissals":2},"D Salunkhe":{"dismissedPlayer":"RP Singh","numberOfdismissals":1},"RR Sarwan":{"dismissedPlayer":"A Nehra","numberOfdismissals":1},"S Sreesanth":{"dismissedPlayer":"DS Kulkarni","numberOfdismissals":1},"VRV Singh":{"dismissedPlayer":"DS Kulkarni","numberOfdismissals":1},"AB Agarkar":{"dismissedPlayer":"SR Watson","numberOfdismissals":2},"M Kartik":{"dismissedPlayer":"L Balaji","numberOfdismissals":2},"LR Shukla":{"dismissedPlayer":"VRV Singh","numberOfdismissals":2},"Shoaib Malik":{"dismissedPlayer":"VRV Singh","numberOfdismissals":1},"MF Maharoof":{"dismissedPlayer":"IK Pathan","numberOfdismissals":1},"SM Katich":{"dismissedPlayer":"R Bhatia","numberOfdismissals":1},"TM Srivastava":{"dismissedPlayer":"VY Mahesh","numberOfdismissals":1},"B Chipli":{"dismissedPlayer":"MS Gony","numberOfdismissals":1},"DW Steyn":{"dismissedPlayer":"SL Malinga","numberOfdismissals":2},"DB Das":{"dismissedPlayer":"Sohail Tanvir","numberOfdismissals":2},"HH Gibbs":{"dismissedPlayer":"Z Khan","numberOfdismissals":3},"DNT Zoysa":{"dismissedPlayer":"S Sreesanth","numberOfdismissals":1},"D Kalyankrishna":{"dismissedPlayer":"IK Pathan","numberOfdismissals":1},"SA Asnodkar":{"dismissedPlayer":"JA Morkel","numberOfdismissals":2},"Salman Butt":{"dismissedPlayer":"Sohail Tanvir","numberOfdismissals":1},"BJ Hodge":{"dismissedPlayer":"Z Khan","numberOfdismissals":2},"Umar Gul":{"dismissedPlayer":"Sohail Tanvir","numberOfdismissals":2},"SP Fleming":{"dismissedPlayer":"VY Mahesh","numberOfdismissals":1},"S Vidyut":{"dismissedPlayer":"GD McGrath","numberOfdismissals":1},"JA Morkel":{"dismissedPlayer":"PP Ojha","numberOfdismissals":3},"LPC Silva":{"dismissedPlayer":"V Kohli","numberOfdismissals":1},"DB Ravi Teja":{"dismissedPlayer":"SL Malinga","numberOfdismissals":3},"RP Singh":{"dismissedPlayer":"DW Steyn","numberOfdismissals":2},"Misbah-ul-Haq":{"dismissedPlayer":"DB Ravi Teja","numberOfdismissals":1},"YV Takawale":{"dismissedPlayer":"VY Mahesh","numberOfdismissals":1},"Mohammad Asif":{"dismissedPlayer":"DS Kulkarni","numberOfdismissals":1},"GD McGrath":{"dismissedPlayer":"DS Kulkarni","numberOfdismissals":1},"S Badrinath":{"dismissedPlayer":"RP Singh","numberOfdismissals":3},"Joginder Sharma":{"dismissedPlayer":"MM Patel","numberOfdismissals":1},"M Muralitharan":{"dismissedPlayer":"Sohail Tanvir","numberOfdismissals":1},"M Ntini":{"dismissedPlayer":"Sohail Tanvir","numberOfdismissals":1},"DT Patil":{"dismissedPlayer":"VRV Singh","numberOfdismissals":1},"A Kumble":{"dismissedPlayer":"IK Pathan","numberOfdismissals":1},"S Anirudha":{"dismissedPlayer":"RP Singh","numberOfdismissals":1},"Sohail Tanvir":{"dismissedPlayer":"A Nehra","numberOfdismissals":1},"SK Trivedi":{"dismissedPlayer":"DJ Bravo","numberOfdismissals":1},"CK Kapugedera":{"dismissedPlayer":"VY Mahesh","numberOfdismissals":1},"A Chopra":{"dismissedPlayer":"DW Steyn","numberOfdismissals":1},"T Taibu":{"dismissedPlayer":"DW Steyn","numberOfdismissals":1},"J Arunkumar":{"dismissedPlayer":"Umar Gul","numberOfdismissals":1},"SP Goswami":{"dismissedPlayer":"MM Patel","numberOfdismissals":2},"R Vinay Kumar":{"dismissedPlayer":"A Singh","numberOfdismissals":3},"AD Mascarenhas":{"dismissedPlayer":"R Bhatia","numberOfdismissals":2},"TM Dilshan":{"dismissedPlayer":"RP Singh","numberOfdismissals":3},"VY Mahesh":{"dismissedPlayer":"LR Shukla","numberOfdismissals":1},"SR Tendulkar":{"dismissedPlayer":"RP Singh","numberOfdismissals":3},"Younis Khan":{"dismissedPlayer":"IK Pathan","numberOfdismissals":1},"Niraj Patel":{"dismissedPlayer":"PP Chawla","numberOfdismissals":1},"Shoaib Akhtar":{"dismissedPlayer":"RR Raje","numberOfdismissals":1},"H Das":{"dismissedPlayer":"CRD Fernando","numberOfdismissals":1},"SD Chitnis":{"dismissedPlayer":"VRV Singh","numberOfdismissals":1},"A Nehra":{"dismissedPlayer":"VRV Singh","numberOfdismissals":1},"VS Yeligati":{"dismissedPlayer":"VRV Singh","numberOfdismissals":1},"MS Gony":{"dismissedPlayer":"P Kumar","numberOfdismissals":1},"L Balaji":{"dismissedPlayer":"DW Steyn","numberOfdismissals":1},"LA Pomersbach":{"dismissedPlayer":"PP Ojha","numberOfdismissals":1},"A Nel":{"dismissedPlayer":"VY Mahesh","numberOfdismissals":1},"A Mukund":{"dismissedPlayer":"Sohail Tanvir","numberOfdismissals":1},"WA Mota":{"dismissedPlayer":"TL Suman","numberOfdismissals":2},"JP Duminy":{"dismissedPlayer":"DP Nannes","numberOfdismissals":2},"A Flintoff":{"dismissedPlayer":"Harbhajan Singh","numberOfdismissals":1},"JD Ryder":{"dismissedPlayer":"IK Pathan","numberOfdismissals":2},"KP Pietersen":{"dismissedPlayer":"Harbhajan Singh","numberOfdismissals":3},"T Henderson":{"dismissedPlayer":"JD Ryder","numberOfdismissals":1},"Kamran Khan":{"dismissedPlayer":"A Kumble","numberOfdismissals":1},"RS Bopara":{"dismissedPlayer":"DJ Bravo","numberOfdismissals":2},"R Bishnoi":{"dismissedPlayer":"M Muralitharan","numberOfdismissals":1},"PC Valthaty":{"dismissedPlayer":"A Mishra","numberOfdismissals":2},"RJ Quiney":{"dismissedPlayer":"A Nehra","numberOfdismissals":2},"Yashpal Singh":{"dismissedPlayer":"SK Warne","numberOfdismissals":1},"Pankaj Singh":{"dismissedPlayer":"IK Pathan","numberOfdismissals":1},"FH Edwards":{"dismissedPlayer":"SL Malinga","numberOfdismissals":1},"AS Raut":{"dismissedPlayer":"PP Chawla","numberOfdismissals":1},"AN Ghosh":{"dismissedPlayer":"AM Nayar","numberOfdismissals":1},"BAW Mendis":{"dismissedPlayer":"SL Malinga","numberOfdismissals":1},"DL Vettori":{"dismissedPlayer":"MM Patel","numberOfdismissals":1},"RE van der Merwe":{"dismissedPlayer":"I Sharma","numberOfdismissals":1},"RR Powar":{"dismissedPlayer":"DJ Bravo","numberOfdismissals":1},"AA Bilakhia":{"dismissedPlayer":"DL Vettori","numberOfdismissals":1},"TL Suman":{"dismissedPlayer":"Harbhajan Singh","numberOfdismissals":3},"Shoaib Ahmed":{"dismissedPlayer":"DP Nannes","numberOfdismissals":1},"GR Napier":{"dismissedPlayer":"CH Gayle","numberOfdismissals":1},"MN van Wyk":{"dismissedPlayer":"GR Napier","numberOfdismissals":1},"LA Carseldine":{"dismissedPlayer":"Y Venugopal Rao","numberOfdismissals":1},"M Vijay":{"dismissedPlayer":"SR Watson","numberOfdismissals":4},"SB Jakati":{"dismissedPlayer":"DP Nannes","numberOfdismissals":1},"M Manhas":{"dismissedPlayer":"R Sharma","numberOfdismissals":2},"RJ Harris":{"dismissedPlayer":"MM Patel","numberOfdismissals":2},"D du Preez":{"dismissedPlayer":"A Singh","numberOfdismissals":1},"RR Raje":{"dismissedPlayer":"R Bhatia","numberOfdismissals":1},"M Morkel":{"dismissedPlayer":"SP Narine","numberOfdismissals":2},"S Tyagi":{"dismissedPlayer":"P Kumar","numberOfdismissals":1},"C Nanda":{"dismissedPlayer":"MM Patel","numberOfdismissals":1},"SL Malinga":{"dismissedPlayer":"WD Parnell","numberOfdismissals":2},"J Botha":{"dismissedPlayer":"Anand Rajan","numberOfdismissals":2},"A Singh":{"dismissedPlayer":"A Mishra","numberOfdismissals":1},"GJ Bailey":{"dismissedPlayer":"MC Henriques","numberOfdismissals":3},"AB McDonald":{"dismissedPlayer":"A Kumble","numberOfdismissals":1},"Y Nagar":{"dismissedPlayer":"R Vinay Kumar","numberOfdismissals":2},"SS Shaikh":{"dismissedPlayer":"J Botha","numberOfdismissals":1},"R Ashwin":{"dismissedPlayer":"Harbhajan Singh","numberOfdismissals":3},"T Thushara":{"dismissedPlayer":"IK Pathan","numberOfdismissals":1},"Mohammad Ashraful":{"dismissedPlayer":"PJ Sangwan","numberOfdismissals":1},"CA Pujara":{"dismissedPlayer":"JH Kallis","numberOfdismissals":2},"Anirudh Singh":{"dismissedPlayer":"LR Shukla","numberOfdismissals":1},"R Sathish":{"dismissedPlayer":"JA Morkel","numberOfdismissals":2},"AA Jhunjhunwala":{"dismissedPlayer":"SL Malinga","numberOfdismissals":1},"P Dogra":{"dismissedPlayer":"SL Malinga","numberOfdismissals":1},"A Uniyal":{"dismissedPlayer":"SL Malinga","numberOfdismissals":1},"MS Bisla":{"dismissedPlayer":"JA Morkel","numberOfdismissals":2},"JM Kemp":{"dismissedPlayer":"PP Ojha","numberOfdismissals":1},"OA Shah":{"dismissedPlayer":"Z Khan","numberOfdismissals":2},"RS Gavaskar":{"dismissedPlayer":"JM Kemp","numberOfdismissals":1},"SE Bond":{"dismissedPlayer":"R Ashwin","numberOfdismissals":1},"DP Nannes":{"dismissedPlayer":"Harbhajan Singh","numberOfdismissals":1},"MJ Lumb":{"dismissedPlayer":"JA Morkel","numberOfdismissals":2},"DR Martyn":{"dismissedPlayer":"P Kumar","numberOfdismissals":1},"S Narwal":{"dismissedPlayer":"P Kumar","numberOfdismissals":1},"AB Barath":{"dismissedPlayer":"PP Ojha","numberOfdismissals":1},"FY Fazal":{"dismissedPlayer":"SE Bond","numberOfdismissals":1},"MD Mishra":{"dismissedPlayer":"P Kumar","numberOfdismissals":2},"S Ladda":{"dismissedPlayer":"WPUJC Vaas","numberOfdismissals":1},"J Theron":{"dismissedPlayer":"L Balaji","numberOfdismissals":1},"SJ Srivastava":{"dismissedPlayer":"SW Tait","numberOfdismissals":1},"R Sharma":{"dismissedPlayer":"MM Patel","numberOfdismissals":2},"AC Voges":{"dismissedPlayer":"JA Morkel","numberOfdismissals":1},"Jaskaran Singh":{"dismissedPlayer":"Harbhajan Singh","numberOfdismissals":1},"KAJ Roach":{"dismissedPlayer":"Z Khan","numberOfdismissals":1},"PD Collingwood":{"dismissedPlayer":"CK Langeveldt","numberOfdismissals":1},"CK Langeveldt":{"dismissedPlayer":"AB McDonald","numberOfdismissals":1},"VS Malik":{"dismissedPlayer":"Z Khan","numberOfdismissals":1},"SW Tait":{"dismissedPlayer":"V Sehwag","numberOfdismissals":1},"A Mithun":{"dismissedPlayer":"A Mishra","numberOfdismissals":1},"AP Dole":{"dismissedPlayer":"RJ Harris","numberOfdismissals":1},"Harmeet Singh":{"dismissedPlayer":"SK Trivedi","numberOfdismissals":1},"R McLaren":{"dismissedPlayer":"R Ashwin","numberOfdismissals":1},"S Sriram":{"dismissedPlayer":"AB Dinda","numberOfdismissals":1},"KP Appanna":{"dismissedPlayer":"RJ Harris","numberOfdismissals":1},"C Madan":{"dismissedPlayer":"AB McDonald","numberOfdismissals":1},"AG Paunikar":{"dismissedPlayer":"R Vinay Kumar","numberOfdismissals":1},"MR Marsh":{"dismissedPlayer":"Yuvraj Singh","numberOfdismissals":1},"B Sumanth":{"dismissedPlayer":"DE Bollinger","numberOfdismissals":1},"RV Gomez":{"dismissedPlayer":"DP Nannes","numberOfdismissals":1},"UBT Chand":{"dismissedPlayer":"B Lee","numberOfdismissals":2},"UT Yadav":{"dismissedPlayer":"Harbhajan Singh","numberOfdismissals":1},"DJ Jacobs":{"dismissedPlayer":"M Morkel","numberOfdismissals":1},"Sunny Singh":{"dismissedPlayer":"M Kartik","numberOfdismissals":1},"AL Menaria":{"dismissedPlayer":"YK Pathan","numberOfdismissals":2},"AUK Pathan":{"dismissedPlayer":"SL Malinga","numberOfdismissals":1},"WD Parnell":{"dismissedPlayer":"SP Narine","numberOfdismissals":2},"JJ van der Wath":{"dismissedPlayer":"DW Steyn","numberOfdismissals":1},"R Ninan":{"dismissedPlayer":"DT Christian","numberOfdismissals":1},"MS Wade":{"dismissedPlayer":"R Sharma","numberOfdismissals":1},"TD Paine":{"dismissedPlayer":"MM Patel","numberOfdismissals":1},"SB Wagh":{"dismissedPlayer":"SL Malinga","numberOfdismissals":1},"JEC Franklin":{"dismissedPlayer":"SB Wagh","numberOfdismissals":1},"Shakib Al Hasan":{"dismissedPlayer":"SL Malinga","numberOfdismissals":3},"S Randiv":{"dismissedPlayer":"SL Malinga","numberOfdismissals":1},"BJ Haddin":{"dismissedPlayer":"J Syed Mohammad","numberOfdismissals":1},"NLTC Perera":{"dismissedPlayer":"A Nehra","numberOfdismissals":2},"JE Taylor":{"dismissedPlayer":"DE Bollinger","numberOfdismissals":1},"NL McCullum":{"dismissedPlayer":"DE Bollinger","numberOfdismissals":1},"RN ten Doeschate":{"dismissedPlayer":"M Morkel","numberOfdismissals":1},"TR Birt":{"dismissedPlayer":"YK Pathan","numberOfdismissals":1},"M Klinger":{"dismissedPlayer":"M Morkel","numberOfdismissals":1},"Harpreet Singh":{"dismissedPlayer":"SR Watson","numberOfdismissals":1},"AC Blizzard":{"dismissedPlayer":"AC Thomas","numberOfdismissals":1},"CA Ingram":{"dismissedPlayer":"SL Malinga","numberOfdismissals":1},"DH Yagnik":{"dismissedPlayer":"Harbhajan Singh","numberOfdismissals":2},"KB Arun Karthik":{"dismissedPlayer":"Iqbal Abdulla","numberOfdismissals":1},"AA Chavan":{"dismissedPlayer":"BJ Hodge","numberOfdismissals":1},"ND Doshi":{"dismissedPlayer":"P Parameswaran","numberOfdismissals":1},"CJ Ferguson":{"dismissedPlayer":"JP Duminy","numberOfdismissals":1},"Y Gnaneswara Rao":{"dismissedPlayer":"DJ Bravo","numberOfdismissals":1},"S Rana":{"dismissedPlayer":"L Balaji","numberOfdismissals":1},"BA Bhatt":{"dismissedPlayer":"Anand Rajan","numberOfdismissals":1},"DE Bollinger":{"dismissedPlayer":"SL Malinga","numberOfdismissals":1},"RE Levi":{"dismissedPlayer":"DW Steyn","numberOfdismissals":2},"HV Patel":{"dismissedPlayer":"A Nehra","numberOfdismissals":2},"DJ Harris":{"dismissedPlayer":"DE Bollinger","numberOfdismissals":1},"KK Cooper":{"dismissedPlayer":"MM Patel","numberOfdismissals":1},"GB Hogg":{"dismissedPlayer":"MM Patel","numberOfdismissals":1},"RR Bhatkal":{"dismissedPlayer":"DE Bollinger","numberOfdismissals":1},"CJ McKay":{"dismissedPlayer":"IK Pathan","numberOfdismissals":1},"N Saini":{"dismissedPlayer":"Z Khan","numberOfdismissals":1},"Azhar Mahmood":{"dismissedPlayer":"A Mishra","numberOfdismissals":2},"AC Thomas":{"dismissedPlayer":"MS Gony","numberOfdismissals":1},"RJ Peterson":{"dismissedPlayer":"M Morkel","numberOfdismissals":1},"A Ashish Reddy":{"dismissedPlayer":"R Vinay Kumar","numberOfdismissals":2},"V Pratap Singh":{"dismissedPlayer":"SL Malinga","numberOfdismissals":1},"MJ Clarke":{"dismissedPlayer":"V Pratap Singh","numberOfdismissals":1},"Gurkeerat Singh":{"dismissedPlayer":"DJ Bravo","numberOfdismissals":2},"AP Majumdar":{"dismissedPlayer":"J Botha","numberOfdismissals":1},"PA Reddy":{"dismissedPlayer":"PP Chawla","numberOfdismissals":1},"AD Russell":{"dismissedPlayer":"P Parameswaran","numberOfdismissals":1},"Sunny Gupta":{"dismissedPlayer":"SB Jakati","numberOfdismissals":1},"MC Juneja":{"dismissedPlayer":"L Balaji","numberOfdismissals":1},"GH Vihari":{"dismissedPlayer":"B Kumar","numberOfdismissals":2},"MDKJ Perera":{"dismissedPlayer":"UT Yadav","numberOfdismissals":1},"B Laughlin":{"dismissedPlayer":"KA Pollard","numberOfdismissals":1},"BMAJ Mendis":{"dismissedPlayer":"KA Pollard","numberOfdismissals":1},"R Rampaul":{"dismissedPlayer":"DJ Bravo","numberOfdismissals":1},"P Awana":{"dismissedPlayer":"JP Faulkner","numberOfdismissals":1},"SMSM Senanayake":{"dismissedPlayer":"P Kumar","numberOfdismissals":1},"BJ Rohrer":{"dismissedPlayer":"JD Unadkat","numberOfdismissals":1},"KL Rahul":{"dismissedPlayer":"DS Kulkarni","numberOfdismissals":3},"J Syed Mohammad":{"dismissedPlayer":"UT Yadav","numberOfdismissals":1},"Q de Kock":{"dismissedPlayer":"AB Dinda","numberOfdismissals":2},"BB Samantray":{"dismissedPlayer":"JP Faulkner","numberOfdismissals":2},"R Dhawan":{"dismissedPlayer":"STR Binny","numberOfdismissals":1},"MG Johnson":{"dismissedPlayer":"JP Faulkner","numberOfdismissals":3},"LJ Wright":{"dismissedPlayer":"Azhar Mahmood","numberOfdismissals":1},"AG Murtaza":{"dismissedPlayer":"CH Gayle","numberOfdismissals":1},"IC Pandey":{"dismissedPlayer":"CH Gayle","numberOfdismissals":1},"X Thalaivan Sargunam":{"dismissedPlayer":"DJ Bravo","numberOfdismissals":1},"DJG Sammy":{"dismissedPlayer":"JP Faulkner","numberOfdismissals":2},"KW Richardson":{"dismissedPlayer":"CH Morris","numberOfdismissals":1},"CM Gautam":{"dismissedPlayer":"SR Watson","numberOfdismissals":1},"UA Birla":{"dismissedPlayer":"Iqbal Abdulla","numberOfdismissals":1},"Parvez Rasool":{"dismissedPlayer":"L Balaji","numberOfdismissals":1},"NJ Maddinson":{"dismissedPlayer":"Mohammed Shami","numberOfdismissals":1},"JDS Neesham":{"dismissedPlayer":"PP Chawla","numberOfdismissals":1},"PV Tambe":{"dismissedPlayer":"R Ashwin","numberOfdismissals":1},"MA Starc":{"dismissedPlayer":"R Bhatia","numberOfdismissals":1},"BR Dunk":{"dismissedPlayer":"DJG Sammy","numberOfdismissals":1},"RR Rossouw":{"dismissedPlayer":"A Nehra","numberOfdismissals":2},"Shivam Sharma":{"dismissedPlayer":"MA Starc","numberOfdismissals":1},"VH Zol":{"dismissedPlayer":"R Tewatia","numberOfdismissals":1},"Imran Tahir":{"dismissedPlayer":"STR Binny","numberOfdismissals":1},"R Shukla":{"dismissedPlayer":"KK Cooper","numberOfdismissals":1},"BE Hendricks":{"dismissedPlayer":"JJ Bumrah","numberOfdismissals":1},"M de Lange":{"dismissedPlayer":"Imran Tahir","numberOfdismissals":1},"S Gopal":{"dismissedPlayer":"WD Parnell","numberOfdismissals":1},"JO Holder":{"dismissedPlayer":"R Vinay Kumar","numberOfdismissals":1},"JD Unadkat":{"dismissedPlayer":"MG Johnson","numberOfdismissals":1},"SA Abbott":{"dismissedPlayer":"Shakib Al Hasan","numberOfdismissals":1},"AN Ahmed":{"dismissedPlayer":"B Kumar","numberOfdismissals":1},"Iqbal Abdulla":{"dismissedPlayer":"KA Pollard","numberOfdismissals":1},"SN Khan":{"dismissedPlayer":"RA Jadeja","numberOfdismissals":1},"D Wiese":{"dismissedPlayer":"DJ Bravo","numberOfdismissals":2},"DJ Muthuswami":{"dismissedPlayer":"D Wiese","numberOfdismissals":1},"Karanveer Singh":{"dismissedPlayer":"MA Starc","numberOfdismissals":1},"Sandeep Sharma":{"dismissedPlayer":"YS Chahal","numberOfdismissals":1},"J Suchith":{"dismissedPlayer":"YS Chahal","numberOfdismissals":1},"C Munro":{"dismissedPlayer":"JJ Bumrah","numberOfdismissals":1},"P Sahu":{"dismissedPlayer":"UT Yadav","numberOfdismissals":1},"M Ashwin":{"dismissedPlayer":"KW Richardson","numberOfdismissals":1},"NS Naik":{"dismissedPlayer":"Mustafizur Rahman","numberOfdismissals":1},"PSP Handscomb":{"dismissedPlayer":"Harbhajan Singh","numberOfdismissals":1},"J Yadav":{"dismissedPlayer":"R Ashwin","numberOfdismissals":1},"UT Khawaja":{"dismissedPlayer":"A Mishra","numberOfdismissals":1},"S Kaushik":{"dismissedPlayer":"Sachin Baby","numberOfdismissals":1},"F Behardien":{"dismissedPlayer":"YS Chahal","numberOfdismissals":1},"KJ Abbott":{"dismissedPlayer":"YS Chahal","numberOfdismissals":1},"ER Dwivedi":{"dismissedPlayer":"SR Watson","numberOfdismissals":1}}